<?xml version="1.0" encoding="UTF-8"?>
<mods xmlns="http://www.loc.gov/mods/v3"
      xmlns:xlink="http://www.w3.org/1999/xlink"
      xmlns:xs="http://www.w3.org/2001/XMLSchema"
      xmlns:xsi="http://www.w3.org/2001/XMLSchema-instance"
      version="3.5">
   <identifier type="local">KDP_1061</identifier>
   <name usage="primary"
         authority="naf"
         valueURI="http://id.loc.gov/authorities/names/n79063202">
      <namePart>United States. Army</namePart>
      <role>
         <roleTerm type="text"
                   authority="marcrelator"
                   valueURI="http://id.loc.gov/vocabulary/relators/cre">Creator</roleTerm>
      </role>
   </name>
   <titleInfo>
      <title>Estes Kefauver and Rep. J.Percy Priest stand with Medal of Honor award winner as Albert Gore looks on</title>
   </titleInfo>
   <typeOfResource>still image</typeOfResource>
   <originInfo>
      <dateCreated>1/7/1953</dateCreated>
      <dateCreated encoding="w3cdtf" keyDate="yes">1953-01-07</dateCreated>
   </originInfo>
   <physicalDescription>
      <extent>1 photograph</extent>
      <form authority="http://vocab.getty.edu/aat/300046300">photographs</form>
      <digitalOrigin>reformatted digital</digitalOrigin>
   </physicalDescription>
   <language>
      <languageTerm type="code" authority="iso639-2b">zxx</languageTerm>
   </language>
   <location>
      <physicalLocation>University of Tennessee, Knoxville. Special Collections</physicalLocation>
      <holdingSimple>
         <copyInformation>
            <shelfLocator>MPA.144</shelfLocator>
         </copyInformation>
      </holdingSimple>
   </location>
   <subject>
      <name authority="naf"
            valueURI="http://id.loc.gov/authorities/names/n79144615">
         <namePart>Kefauver, Estes, 1903-1963</namePart>
      </name>
   </subject>
   <subject>
      <name>
         <namePart>Gore, Albert, 1907-1998</namePart>
      </name>
   </subject>
   <subject>
      <name authority="naf"
            valueURI="http://id.loc.gov/authorities/names/no2012099463">
         <namePart>Priest, James Percy, 1900-1956</namePart>
      </name>
   </subject>
   <relatedItem type="host" displayLabel="Project">
      <titleInfo>
         <title>Estes Kefauver Image Collection</title>
      </titleInfo>
   </relatedItem>
   <relatedItem type="host" displayLabel="Collection">
      <titleInfo>
         <title>Estes Kefauver Papers</title>
      </titleInfo>
   </relatedItem>
   <accessCondition type="use and reproduction">Public domain.</accessCondition>
   <recordInfo>
      <recordIdentifier>record_KDP_1061</recordIdentifier>
      <recordContentSource>University of Tennessee, Knoxville. Libraries</recordContentSource>
      <languageOfCataloging>
         <languageTerm type="code" authority="iso639-2b">eng</languageTerm>
      </languageOfCataloging>
      <recordOrigin>Created and edited in general conformance to MODS Guidelines (Version 3.5).</recordOrigin>
   </recordInfo>
</mods>
